{"is_source_file": true, "format": "JavaScript (React)", "description": "This file initializes a React application, rendering the main App component into the DOM element with id 'root'. It sets up the React environment and mounts the application on startup.", "external_files": ["react", "react-dom/client", "./index.css", "./App"], "external_methods": ["ReactDOM.createRoot", "root.render"], "published": ["React", "ReactDOM"], "classes": [], "methods": [{"name": "ReactDOM.createRoot", "description": "Creates a root to render the React component tree."}, {"name": "root.render", "description": "Renders the React component into the specified DOM node."}], "calls": ["ReactDOM.createRoot", "root.render", "document.getElementById"], "search-terms": ["React", "index.js", "render", "ReactDOM", "createRoot", "StrictMode", "App component"], "state": 2, "file_id": 12, "knowledge_revision": 23, "git_revision": "c80ac608d580defb3f42ca2a9f9c109a6257d906", "ctags": [{"_type": "tag", "name": "root", "path": "/home/kavia/workspace/code-generation/vendor-network-management-platform-4800-4810/multi_vendor_frontend/src/index.js", "pattern": "/^const root = ReactDOM.createRoot(document.getElementById('root'));$/", "language": "JavaScript", "kind": "constant"}], "hash": "9fc5841375336fc175b49f8767a11383", "format-version": 4, "code-base-name": "multi_vendor_frontend", "filename": "multi_vendor_frontend/src/index.js", "revision_history": [{"23": "c80ac608d580defb3f42ca2a9f9c109a6257d906"}]}